couchdb_cluster_admin/__init__.py
couchdb_cluster_admin/add_replica_node.py
couchdb_cluster_admin/copy_db_to_new_cluster.py
couchdb_cluster_admin/describe.py
couchdb_cluster_admin/doc_models.py
couchdb_cluster_admin/file_plan.py
couchdb_cluster_admin/remove_node.py
couchdb_cluster_admin/replicate_db_to_new_node.py
couchdb_cluster_admin/suggest_shard_allocation.py
couchdb_cluster_admin/utils.py
couchdb_cluster_admin-0.7.4.dist-info/licenses/LICENSE
couchdb_cluster_admin-0.7.4.dist-info/METADATA
couchdb_cluster_admin-0.7.4.dist-info/WHEEL
couchdb_cluster_admin-0.7.4.dist-info/top_level.txt
couchdb_cluster_admin-0.7.4.dist-info/RECORD
