Metadata-Version: 2.4
Name: couchdb-cluster-admin
Version: 0.7.4
Summary: Utility for managing multi-node couchdb clusters
Author-email: Dimagi <dev@dimagi.com>
License: BSD 3-Clause License
Project-URL: Home, https://github.com/dimagi/couchdb-cluster-admin
Classifier: Development Status :: 3 - Alpha
Classifier: Environment :: Web Environment
Classifier: Intended Audience :: Developers
Classifier: License :: OSI Approved :: BSD License
Classifier: Operating System :: OS Independent
Classifier: Programming Language :: Python
Classifier: Programming Language :: Python :: 3
Classifier: Programming Language :: Python :: 3.10
Classifier: Topic :: Software Development :: Libraries :: Python Modules
Requires-Python: >=3.10
License-File: LICENSE
Requires-Dist: argparse>=1.4
Requires-Dist: dimagi-memoized
Requires-Dist: gevent
Requires-Dist: jsonobject
Requires-Dist: PyYAML
Requires-Dist: requests
Dynamic: license-file
